[
  {
    "platform": "GitHub",
    "name": "sailpoint-oss/colab-saas-conn-sailpoint-identity-fusion",
    "timestamp": "2025-12-01T00:39:58.159Z",
    "metrics": {
      "stars": 6,
      "forks": 6,
      "watchers": 4,
      "totalIssues": 4,
      "openIssues": 3,
      "closedIssues": 1,
      "language": "TypeScript",
      "size": 6795,
      "repositoryAge": 607,
      "lastActivity": 4,
      "releaseCount": 9,
      "totalReleaseDownloads": 69,
      "latestReleaseDownloads": 2,
      "viewsCount": 419,
      "uniqueVisitors": 65,
      "latestRelease": "v1.3.1",
      "clonesCount": 55,
      "topics": 0,
      "license": "MIT License",
      "defaultBranch": "main",
      "downloadsTotal": 69,
      "downloadRange": [
        {
          "day": "2025-02-18T21:21:37Z",
          "downloads": 6,
          "tagName": "v0.0.5"
        },
        {
          "day": "2025-02-24T21:28:33Z",
          "downloads": 5,
          "tagName": "v1.0.0"
        },
        {
          "day": "2025-03-17T15:43:09Z",
          "downloads": 18,
          "tagName": "v1.1.0"
        },
        {
          "day": "2025-07-18T15:34:47Z",
          "downloads": 6,
          "tagName": "v1.1.1"
        },
        {
          "day": "2025-08-06T19:34:26Z",
          "downloads": 5,
          "tagName": "v1.1.2"
        },
        {
          "day": "2025-09-16T13:32:31Z",
          "downloads": 5,
          "tagName": "v1.2.1"
        },
        {
          "day": "2025-09-18T13:09:47Z",
          "downloads": 20,
          "tagName": "v1.2.2"
        },
        {
          "day": "2025-11-20T20:00:03Z",
          "downloads": 2,
          "tagName": "v1.3.0"
        },
        {
          "day": "2025-11-26T14:47:49Z",
          "downloads": 2,
          "tagName": "v1.3.1"
        }
      ],
      "assetTotalsByName": {
        "identity_zip": 69
      },
      "assetReleaseSeries": {
        "identity_zip": [
          {
            "tagName": "v1.3.1",
            "day": "2025-11-26T14:47:49Z",
            "downloads": 2
          },
          {
            "tagName": "v1.3.0",
            "day": "2025-11-20T20:00:03Z",
            "downloads": 2
          },
          {
            "tagName": "v1.2.2",
            "day": "2025-09-18T13:09:47Z",
            "downloads": 20
          },
          {
            "tagName": "v1.2.1",
            "day": "2025-09-16T13:32:31Z",
            "downloads": 5
          },
          {
            "tagName": "v1.1.2",
            "day": "2025-08-06T19:34:26Z",
            "downloads": 5
          },
          {
            "tagName": "v1.1.1",
            "day": "2025-07-18T15:34:47Z",
            "downloads": 6
          },
          {
            "tagName": "v1.1.0",
            "day": "2025-03-17T15:43:09Z",
            "downloads": 18
          },
          {
            "tagName": "v1.0.0",
            "day": "2025-02-24T21:28:33Z",
            "downloads": 5
          },
          {
            "tagName": "v0.0.5",
            "day": "2025-02-18T21:21:37Z",
            "downloads": 6
          }
        ]
      },
      "assetTotalsByParsedKey": {
        "identity_zip": 69
      },
      "totalsByOs": {},
      "totalsByArch": {},
      "totalsByFormat": {
        "zip": 69
      },
      "totalsByVariant": {},
      "attributeReleaseSeries": {
        "os": {},
        "arch": {},
        "format": {
          "zip": {
            "v1.3.1": 2,
            "v1.3.0": 2,
            "v1.2.2": 20,
            "v1.2.1": 5,
            "v1.1.2": 5,
            "v1.1.1": 6,
            "v1.1.0": 18,
            "v1.0.0": 5,
            "v0.0.5": 6
          }
        },
        "variant": {},
        "version": {}
      },
      "assetAttributesByKey": {
        "identity_zip": {
          "project": "identity",
          "format": "zip"
        }
      }
    }
  },
  {
    "platform": "GitHub",
    "name": "sailpoint-oss/colab-saas-conn-attribute-generator",
    "timestamp": "2025-12-01T00:39:58.104Z",
    "metrics": {
      "stars": 0,
      "forks": 1,
      "watchers": 0,
      "totalIssues": 0,
      "openIssues": 0,
      "closedIssues": 0,
      "language": "TypeScript",
      "size": 991,
      "repositoryAge": 158,
      "lastActivity": 5,
      "releaseCount": 0,
      "totalReleaseDownloads": 0,
      "latestReleaseDownloads": 0,
      "viewsCount": 67,
      "uniqueVisitors": 11,
      "latestRelease": null,
      "clonesCount": 19,
      "topics": 0,
      "license": "MIT License",
      "defaultBranch": "main",
      "downloadsTotal": 0,
      "downloadRange": [],
      "assetTotalsByName": {},
      "assetReleaseSeries": {},
      "assetTotalsByParsedKey": {},
      "totalsByOs": {},
      "totalsByArch": {},
      "totalsByFormat": {},
      "totalsByVariant": {},
      "attributeReleaseSeries": {
        "os": {},
        "arch": {},
        "format": {},
        "variant": {},
        "version": {}
      },
      "assetAttributesByKey": {}
    }
  },
  {
    "platform": "GitHub",
    "name": "sailpoint-oss/colab-saas-conn-proxy-entitlements",
    "timestamp": "2025-12-01T00:39:58.149Z",
    "metrics": {
      "stars": 0,
      "forks": 0,
      "watchers": 0,
      "totalIssues": 0,
      "openIssues": 0,
      "closedIssues": 0,
      "language": "TypeScript",
      "size": 839,
      "repositoryAge": 158,
      "lastActivity": 5,
      "releaseCount": 0,
      "totalReleaseDownloads": 0,
      "latestReleaseDownloads": 0,
      "viewsCount": 12,
      "uniqueVisitors": 10,
      "latestRelease": null,
      "clonesCount": 13,
      "topics": 0,
      "license": "MIT License",
      "defaultBranch": "main",
      "downloadsTotal": 0,
      "downloadRange": [],
      "assetTotalsByName": {},
      "assetReleaseSeries": {},
      "assetTotalsByParsedKey": {},
      "totalsByOs": {},
      "totalsByArch": {},
      "totalsByFormat": {},
      "totalsByVariant": {},
      "attributeReleaseSeries": {
        "os": {},
        "arch": {},
        "format": {},
        "variant": {},
        "version": {}
      },
      "assetAttributesByKey": {}
    }
  },
  {
    "platform": "GitHub",
    "name": "sailpoint-oss/colab-siem-plugin",
    "timestamp": "2025-12-01T00:39:58.207Z",
    "metrics": {
      "stars": 3,
      "forks": 2,
      "watchers": 0,
      "totalIssues": 0,
      "openIssues": 0,
      "closedIssues": 0,
      "language": "CSS",
      "size": 2122,
      "repositoryAge": 795,
      "lastActivity": 23,
      "releaseCount": 0,
      "totalReleaseDownloads": 0,
      "latestReleaseDownloads": 0,
      "viewsCount": 84,
      "uniqueVisitors": 16,
      "latestRelease": null,
      "clonesCount": 5,
      "topics": 1,
      "license": "MIT License",
      "defaultBranch": "main",
      "downloadsTotal": 0,
      "downloadRange": [],
      "assetTotalsByName": {},
      "assetReleaseSeries": {},
      "assetTotalsByParsedKey": {},
      "totalsByOs": {},
      "totalsByArch": {},
      "totalsByFormat": {},
      "totalsByVariant": {},
      "attributeReleaseSeries": {
        "os": {},
        "arch": {},
        "format": {},
        "variant": {},
        "version": {}
      },
      "assetAttributesByKey": {}
    }
  },
  {
    "platform": "GitHub",
    "name": "sailpoint-oss/colab-isc-extended-workflow-helper",
    "timestamp": "2025-12-01T00:39:58.124Z",
    "metrics": {
      "stars": 0,
      "forks": 2,
      "watchers": 0,
      "totalIssues": 0,
      "openIssues": 0,
      "closedIssues": 0,
      "language": "Java",
      "size": 658,
      "repositoryAge": 73,
      "lastActivity": 66,
      "releaseCount": 0,
      "totalReleaseDownloads": 0,
      "latestReleaseDownloads": 0,
      "viewsCount": 16,
      "uniqueVisitors": 5,
      "latestRelease": null,
      "clonesCount": 4,
      "topics": 0,
      "license": "MIT License",
      "defaultBranch": "main",
      "downloadsTotal": 0,
      "downloadRange": [],
      "assetTotalsByName": {},
      "assetReleaseSeries": {},
      "assetTotalsByParsedKey": {},
      "totalsByOs": {},
      "totalsByArch": {},
      "totalsByFormat": {},
      "totalsByVariant": {},
      "attributeReleaseSeries": {
        "os": {},
        "arch": {},
        "format": {},
        "variant": {},
        "version": {}
      },
      "assetAttributesByKey": {}
    }
  },
  {
    "platform": "GitHub",
    "name": "sailpoint-oss/colab-saas-conn-prisma-sase",
    "timestamp": "2025-12-01T00:39:58.182Z",
    "metrics": {
      "stars": 0,
      "forks": 2,
      "watchers": 0,
      "totalIssues": 0,
      "openIssues": 0,
      "closedIssues": 0,
      "language": "TypeScript",
      "size": 598,
      "repositoryAge": 492,
      "lastActivity": 80,
      "releaseCount": 0,
      "totalReleaseDownloads": 0,
      "latestReleaseDownloads": 0,
      "viewsCount": 2,
      "uniqueVisitors": 2,
      "latestRelease": null,
      "clonesCount": 7,
      "topics": 0,
      "license": "MIT License",
      "defaultBranch": "main",
      "downloadsTotal": 0,
      "downloadRange": [],
      "assetTotalsByName": {},
      "assetReleaseSeries": {},
      "assetTotalsByParsedKey": {},
      "totalsByOs": {},
      "totalsByArch": {},
      "totalsByFormat": {},
      "totalsByVariant": {},
      "attributeReleaseSeries": {
        "os": {},
        "arch": {},
        "format": {},
        "variant": {},
        "version": {}
      },
      "assetAttributesByKey": {}
    }
  },
  {
    "platform": "GitHub",
    "name": "sailpoint-oss/colab-saas-conn-pan-customer-service-portal",
    "timestamp": "2025-12-01T00:39:58.088Z",
    "metrics": {
      "stars": 0,
      "forks": 1,
      "watchers": 0,
      "totalIssues": 0,
      "openIssues": 0,
      "closedIssues": 0,
      "language": "TypeScript",
      "size": 607,
      "repositoryAge": 492,
      "lastActivity": 81,
      "releaseCount": 0,
      "totalReleaseDownloads": 0,
      "latestReleaseDownloads": 0,
      "viewsCount": 6,
      "uniqueVisitors": 4,
      "latestRelease": null,
      "clonesCount": 12,
      "topics": 0,
      "license": "MIT License",
      "defaultBranch": "main",
      "downloadsTotal": 0,
      "downloadRange": [],
      "assetTotalsByName": {},
      "assetReleaseSeries": {},
      "assetTotalsByParsedKey": {},
      "totalsByOs": {},
      "totalsByArch": {},
      "totalsByFormat": {},
      "totalsByVariant": {},
      "attributeReleaseSeries": {
        "os": {},
        "arch": {},
        "format": {},
        "variant": {},
        "version": {}
      },
      "assetAttributesByKey": {}
    }
  },
  {
    "platform": "GitHub",
    "name": "sailpoint-oss/colab-iiq-roles-with-deleted-entitlements",
    "timestamp": "2025-12-01T00:39:58.254Z",
    "metrics": {
      "stars": 0,
      "forks": 1,
      "watchers": 0,
      "totalIssues": 0,
      "openIssues": 0,
      "closedIssues": 0,
      "language": null,
      "size": 397,
      "repositoryAge": 86,
      "lastActivity": 86,
      "releaseCount": 0,
      "totalReleaseDownloads": 0,
      "latestReleaseDownloads": 0,
      "viewsCount": 2,
      "uniqueVisitors": 1,
      "latestRelease": null,
      "clonesCount": 3,
      "topics": 0,
      "license": "MIT License",
      "defaultBranch": "main",
      "downloadsTotal": 0,
      "downloadRange": [],
      "assetTotalsByName": {},
      "assetReleaseSeries": {},
      "assetTotalsByParsedKey": {},
      "totalsByOs": {},
      "totalsByArch": {},
      "totalsByFormat": {},
      "totalsByVariant": {},
      "attributeReleaseSeries": {
        "os": {},
        "arch": {},
        "format": {},
        "variant": {},
        "version": {}
      },
      "assetAttributesByKey": {}
    }
  },
  {
    "platform": "GitHub",
    "name": "sailpoint-oss/colab-stunt-script",
    "timestamp": "2025-12-01T00:39:58.140Z",
    "metrics": {
      "stars": 4,
      "forks": 0,
      "watchers": 2,
      "totalIssues": 0,
      "openIssues": 0,
      "closedIssues": 0,
      "language": "Shell",
      "size": 506,
      "repositoryAge": 795,
      "lastActivity": 103,
      "releaseCount": 0,
      "totalReleaseDownloads": 0,
      "latestReleaseDownloads": 0,
      "viewsCount": 24,
      "uniqueVisitors": 18,
      "latestRelease": null,
      "clonesCount": 15,
      "topics": 1,
      "license": "MIT License",
      "defaultBranch": "main",
      "downloadsTotal": 0,
      "downloadRange": [],
      "assetTotalsByName": {},
      "assetReleaseSeries": {},
      "assetTotalsByParsedKey": {},
      "totalsByOs": {},
      "totalsByArch": {},
      "totalsByFormat": {},
      "totalsByVariant": {},
      "attributeReleaseSeries": {
        "os": {},
        "arch": {},
        "format": {},
        "variant": {},
        "version": {}
      },
      "assetAttributesByKey": {}
    }
  },
  {
    "platform": "GitHub",
    "name": "sailpoint-oss/colab-saas-conn-outlook-out-of-office",
    "timestamp": "2025-12-01T00:39:58.228Z",
    "metrics": {
      "stars": 1,
      "forks": 1,
      "watchers": 1,
      "totalIssues": 0,
      "openIssues": 0,
      "closedIssues": 0,
      "language": "TypeScript",
      "size": 1545,
      "repositoryAge": 746,
      "lastActivity": 104,
      "releaseCount": 0,
      "totalReleaseDownloads": 0,
      "latestReleaseDownloads": 0,
      "viewsCount": 1,
      "uniqueVisitors": 1,
      "latestRelease": null,
      "clonesCount": 4,
      "topics": 0,
      "license": "MIT License",
      "defaultBranch": "main",
      "downloadsTotal": 0,
      "downloadRange": [],
      "assetTotalsByName": {},
      "assetReleaseSeries": {},
      "assetTotalsByParsedKey": {},
      "totalsByOs": {},
      "totalsByArch": {},
      "totalsByFormat": {},
      "totalsByVariant": {},
      "attributeReleaseSeries": {
        "os": {},
        "arch": {},
        "format": {},
        "variant": {},
        "version": {}
      },
      "assetAttributesByKey": {}
    }
  },
  {
    "platform": "GitHub",
    "name": "sailpoint-oss/colab-saas-conn-access-management",
    "timestamp": "2025-12-01T00:39:58.259Z",
    "metrics": {
      "stars": 0,
      "forks": 0,
      "watchers": 0,
      "totalIssues": 0,
      "openIssues": 0,
      "closedIssues": 0,
      "language": "TypeScript",
      "size": 416,
      "repositoryAge": 158,
      "lastActivity": 110,
      "releaseCount": 0,
      "totalReleaseDownloads": 0,
      "latestReleaseDownloads": 0,
      "viewsCount": 17,
      "uniqueVisitors": 6,
      "latestRelease": null,
      "clonesCount": 5,
      "topics": 0,
      "license": "MIT License",
      "defaultBranch": "main",
      "downloadsTotal": 0,
      "downloadRange": [],
      "assetTotalsByName": {},
      "assetReleaseSeries": {},
      "assetTotalsByParsedKey": {},
      "totalsByOs": {},
      "totalsByArch": {},
      "totalsByFormat": {},
      "totalsByVariant": {},
      "attributeReleaseSeries": {
        "os": {},
        "arch": {},
        "format": {},
        "variant": {},
        "version": {}
      },
      "assetAttributesByKey": {}
    }
  },
  {
    "platform": "GitHub",
    "name": "sailpoint-oss/colab-saas-customizer-entra-id-plus",
    "timestamp": "2025-12-01T00:39:58.179Z",
    "metrics": {
      "stars": 0,
      "forks": 0,
      "watchers": 1,
      "totalIssues": 0,
      "openIssues": 0,
      "closedIssues": 0,
      "language": "TypeScript",
      "size": 407,
      "repositoryAge": 158,
      "lastActivity": 110,
      "releaseCount": 0,
      "totalReleaseDownloads": 0,
      "latestReleaseDownloads": 0,
      "viewsCount": 16,
      "uniqueVisitors": 6,
      "latestRelease": null,
      "clonesCount": 5,
      "topics": 0,
      "license": "MIT License",
      "defaultBranch": "main",
      "downloadsTotal": 0,
      "downloadRange": [],
      "assetTotalsByName": {},
      "assetReleaseSeries": {},
      "assetTotalsByParsedKey": {},
      "totalsByOs": {},
      "totalsByArch": {},
      "totalsByFormat": {},
      "totalsByVariant": {},
      "attributeReleaseSeries": {
        "os": {},
        "arch": {},
        "format": {},
        "variant": {},
        "version": {}
      },
      "assetAttributesByKey": {}
    }
  },
  {
    "platform": "GitHub",
    "name": "sailpoint-oss/colab-saas-conn-search-loopback",
    "timestamp": "2025-12-01T00:39:58.270Z",
    "metrics": {
      "stars": 0,
      "forks": 1,
      "watchers": 0,
      "totalIssues": 0,
      "openIssues": 0,
      "closedIssues": 0,
      "language": "TypeScript",
      "size": 687,
      "repositoryAge": 311,
      "lastActivity": 111,
      "releaseCount": 0,
      "totalReleaseDownloads": 0,
      "latestReleaseDownloads": 0,
      "viewsCount": 9,
      "uniqueVisitors": 6,
      "latestRelease": null,
      "clonesCount": 5,
      "topics": 0,
      "license": "MIT License",
      "defaultBranch": "main",
      "downloadsTotal": 0,
      "downloadRange": [],
      "assetTotalsByName": {},
      "assetReleaseSeries": {},
      "assetTotalsByParsedKey": {},
      "totalsByOs": {},
      "totalsByArch": {},
      "totalsByFormat": {},
      "totalsByVariant": {},
      "attributeReleaseSeries": {
        "os": {},
        "arch": {},
        "format": {},
        "variant": {},
        "version": {}
      },
      "assetAttributesByKey": {}
    }
  },
  {
    "platform": "GitHub",
    "name": "sailpoint-oss/colab-sailpoint-zapier-integration",
    "timestamp": "2025-12-01T00:39:58.155Z",
    "metrics": {
      "stars": 1,
      "forks": 1,
      "watchers": 0,
      "totalIssues": 0,
      "openIssues": 0,
      "closedIssues": 0,
      "language": "JavaScript",
      "size": 494,
      "repositoryAge": 796,
      "lastActivity": 131,
      "releaseCount": 0,
      "totalReleaseDownloads": 0,
      "latestReleaseDownloads": 0,
      "viewsCount": 1,
      "uniqueVisitors": 1,
      "latestRelease": null,
      "clonesCount": 6,
      "topics": 1,
      "license": "MIT License",
      "defaultBranch": "main",
      "downloadsTotal": 0,
      "downloadRange": [],
      "assetTotalsByName": {},
      "assetReleaseSeries": {},
      "assetTotalsByParsedKey": {},
      "totalsByOs": {},
      "totalsByArch": {},
      "totalsByFormat": {},
      "totalsByVariant": {},
      "attributeReleaseSeries": {
        "os": {},
        "arch": {},
        "format": {},
        "variant": {},
        "version": {}
      },
      "assetAttributesByKey": {}
    }
  },
  {
    "platform": "GitHub",
    "name": "sailpoint-oss/colab-events-dashboard-plugin",
    "timestamp": "2025-12-01T00:39:58.168Z",
    "metrics": {
      "stars": 0,
      "forks": 1,
      "watchers": 0,
      "totalIssues": 0,
      "openIssues": 0,
      "closedIssues": 0,
      "language": "Java",
      "size": 547,
      "repositoryAge": 158,
      "lastActivity": 135,
      "releaseCount": 1,
      "totalReleaseDownloads": 7,
      "latestReleaseDownloads": 7,
      "viewsCount": 26,
      "uniqueVisitors": 6,
      "latestRelease": "v1.0",
      "clonesCount": 4,
      "topics": 0,
      "license": "MIT License",
      "defaultBranch": "main",
      "downloadsTotal": 7,
      "downloadRange": [
        {
          "day": "2025-07-18T04:57:05Z",
          "downloads": 7,
          "tagName": "v1.0"
        }
      ],
      "assetTotalsByName": {
        "eventsdashboardplugin_zip": 7
      },
      "assetReleaseSeries": {
        "eventsdashboardplugin_zip": [
          {
            "tagName": "v1.0",
            "day": "2025-07-18T04:57:05Z",
            "downloads": 7
          }
        ]
      },
      "assetTotalsByParsedKey": {
        "eventsdashboardplugin_zip": 7
      },
      "totalsByOs": {},
      "totalsByArch": {},
      "totalsByFormat": {
        "zip": 7
      },
      "totalsByVariant": {},
      "attributeReleaseSeries": {
        "os": {},
        "arch": {},
        "format": {
          "zip": {
            "v1.0": 7
          }
        },
        "variant": {},
        "version": {}
      },
      "assetAttributesByKey": {
        "eventsdashboardplugin_zip": {
          "project": "EventsDashboardPlugin",
          "format": "zip"
        }
      }
    }
  },
  {
    "platform": "GitHub",
    "name": "sailpoint-oss/colab-motd-plugin",
    "timestamp": "2025-12-01T00:39:58.131Z",
    "metrics": {
      "stars": 4,
      "forks": 0,
      "watchers": 0,
      "totalIssues": 0,
      "openIssues": 0,
      "closedIssues": 0,
      "language": "JavaScript",
      "size": 27236,
      "repositoryAge": 584,
      "lastActivity": 141,
      "releaseCount": 0,
      "totalReleaseDownloads": 0,
      "latestReleaseDownloads": 0,
      "viewsCount": 15,
      "uniqueVisitors": 2,
      "latestRelease": null,
      "clonesCount": 5,
      "topics": 0,
      "license": "MIT License",
      "defaultBranch": "main",
      "downloadsTotal": 0,
      "downloadRange": [],
      "assetTotalsByName": {},
      "assetReleaseSeries": {},
      "assetTotalsByParsedKey": {},
      "totalsByOs": {},
      "totalsByArch": {},
      "totalsByFormat": {},
      "totalsByVariant": {},
      "attributeReleaseSeries": {
        "os": {},
        "arch": {},
        "format": {},
        "variant": {},
        "version": {}
      },
      "assetAttributesByKey": {}
    }
  },
  {
    "platform": "GitHub",
    "name": "sailpoint-oss/colab-saas-conn-genetec-clearid",
    "timestamp": "2025-12-01T00:39:58.399Z",
    "metrics": {
      "stars": 2,
      "forks": 1,
      "watchers": 0,
      "totalIssues": 1,
      "openIssues": 1,
      "closedIssues": 0,
      "language": "TypeScript",
      "size": 411,
      "repositoryAge": 795,
      "lastActivity": 166,
      "releaseCount": 0,
      "totalReleaseDownloads": 0,
      "latestReleaseDownloads": 0,
      "viewsCount": 23,
      "uniqueVisitors": 6,
      "latestRelease": null,
      "clonesCount": 6,
      "topics": 1,
      "license": "MIT License",
      "defaultBranch": "main",
      "downloadsTotal": 0,
      "downloadRange": [],
      "assetTotalsByName": {},
      "assetReleaseSeries": {},
      "assetTotalsByParsedKey": {},
      "totalsByOs": {},
      "totalsByArch": {},
      "totalsByFormat": {},
      "totalsByVariant": {},
      "attributeReleaseSeries": {
        "os": {},
        "arch": {},
        "format": {},
        "variant": {},
        "version": {}
      },
      "assetAttributesByKey": {}
    }
  },
  {
    "platform": "GitHub",
    "name": "sailpoint-oss/colab-iiq-resilient-actions",
    "timestamp": "2025-12-01T00:39:58.520Z",
    "metrics": {
      "stars": 0,
      "forks": 1,
      "watchers": 0,
      "totalIssues": 0,
      "openIssues": 0,
      "closedIssues": 0,
      "language": null,
      "size": 400,
      "repositoryAge": 171,
      "lastActivity": 171,
      "releaseCount": 0,
      "totalReleaseDownloads": 0,
      "latestReleaseDownloads": 0,
      "viewsCount": 1,
      "uniqueVisitors": 1,
      "latestRelease": null,
      "clonesCount": 5,
      "topics": 0,
      "license": "MIT License",
      "defaultBranch": "main",
      "downloadsTotal": 0,
      "downloadRange": [],
      "assetTotalsByName": {},
      "assetReleaseSeries": {},
      "assetTotalsByParsedKey": {},
      "totalsByOs": {},
      "totalsByArch": {},
      "totalsByFormat": {},
      "totalsByVariant": {},
      "attributeReleaseSeries": {
        "os": {},
        "arch": {},
        "format": {},
        "variant": {},
        "version": {}
      },
      "assetAttributesByKey": {}
    }
  },
  {
    "platform": "GitHub",
    "name": "sailpoint-oss/colab-isc-PsAttributeSyncValidator",
    "timestamp": "2025-12-01T00:39:58.237Z",
    "metrics": {
      "stars": 0,
      "forks": 1,
      "watchers": 0,
      "totalIssues": 0,
      "openIssues": 0,
      "closedIssues": 0,
      "language": null,
      "size": 397,
      "repositoryAge": 181,
      "lastActivity": 181,
      "releaseCount": 0,
      "totalReleaseDownloads": 0,
      "latestReleaseDownloads": 0,
      "viewsCount": 0,
      "uniqueVisitors": 0,
      "latestRelease": null,
      "clonesCount": 4,
      "topics": 0,
      "license": "MIT License",
      "defaultBranch": "main",
      "downloadsTotal": 0,
      "downloadRange": [],
      "assetTotalsByName": {},
      "assetReleaseSeries": {},
      "assetTotalsByParsedKey": {},
      "totalsByOs": {},
      "totalsByArch": {},
      "totalsByFormat": {},
      "totalsByVariant": {},
      "attributeReleaseSeries": {
        "os": {},
        "arch": {},
        "format": {},
        "variant": {},
        "version": {}
      },
      "assetAttributesByKey": {}
    }
  },
  {
    "platform": "GitHub",
    "name": "sailpoint-oss/colab-saas-conn-identitynow-orphan-accounts",
    "timestamp": "2025-12-01T00:39:58.329Z",
    "metrics": {
      "stars": 2,
      "forks": 6,
      "watchers": 0,
      "totalIssues": 0,
      "openIssues": 0,
      "closedIssues": 0,
      "language": "TypeScript",
      "size": 413,
      "repositoryAge": 795,
      "lastActivity": 184,
      "releaseCount": 0,
      "totalReleaseDownloads": 0,
      "latestReleaseDownloads": 0,
      "viewsCount": 3,
      "uniqueVisitors": 3,
      "latestRelease": null,
      "clonesCount": 5,
      "topics": 1,
      "license": "MIT License",
      "defaultBranch": "main",
      "downloadsTotal": 0,
      "downloadRange": [],
      "assetTotalsByName": {},
      "assetReleaseSeries": {},
      "assetTotalsByParsedKey": {},
      "totalsByOs": {},
      "totalsByArch": {},
      "totalsByFormat": {},
      "totalsByVariant": {},
      "attributeReleaseSeries": {
        "os": {},
        "arch": {},
        "format": {},
        "variant": {},
        "version": {}
      },
      "assetAttributesByKey": {}
    }
  },
  {
    "platform": "GitHub",
    "name": "sailpoint-oss/colab-saas-conn-peloton-platform",
    "timestamp": "2025-12-01T00:39:58.236Z",
    "metrics": {
      "stars": 0,
      "forks": 1,
      "watchers": 0,
      "totalIssues": 0,
      "openIssues": 0,
      "closedIssues": 0,
      "language": "TypeScript",
      "size": 460,
      "repositoryAge": 215,
      "lastActivity": 215,
      "releaseCount": 0,
      "totalReleaseDownloads": 0,
      "latestReleaseDownloads": 0,
      "viewsCount": 1,
      "uniqueVisitors": 1,
      "latestRelease": null,
      "clonesCount": 5,
      "topics": 0,
      "license": "MIT License",
      "defaultBranch": "main",
      "downloadsTotal": 0,
      "downloadRange": [],
      "assetTotalsByName": {},
      "assetReleaseSeries": {},
      "assetTotalsByParsedKey": {},
      "totalsByOs": {},
      "totalsByArch": {},
      "totalsByFormat": {},
      "totalsByVariant": {},
      "attributeReleaseSeries": {
        "os": {},
        "arch": {},
        "format": {},
        "variant": {},
        "version": {}
      },
      "assetAttributesByKey": {}
    }
  },
  {
    "platform": "GitHub",
    "name": "sailpoint-oss/colab-non-employee-risk-management-splunk-addon",
    "timestamp": "2025-12-01T00:39:58.198Z",
    "metrics": {
      "stars": 1,
      "forks": 1,
      "watchers": 0,
      "totalIssues": 0,
      "openIssues": 0,
      "closedIssues": 0,
      "language": "Python",
      "size": 8515,
      "repositoryAge": 373,
      "lastActivity": 237,
      "releaseCount": 1,
      "totalReleaseDownloads": 0,
      "latestReleaseDownloads": 0,
      "viewsCount": 1,
      "uniqueVisitors": 1,
      "latestRelease": "v1.0.0",
      "clonesCount": 5,
      "topics": 0,
      "license": "MIT License",
      "defaultBranch": "main",
      "downloadsTotal": 0,
      "downloadRange": [
        {
          "day": "2025-04-03T17:55:58Z",
          "downloads": 0,
          "tagName": "v1.0.0"
        }
      ],
      "assetTotalsByName": {},
      "assetReleaseSeries": {},
      "assetTotalsByParsedKey": {},
      "totalsByOs": {},
      "totalsByArch": {},
      "totalsByFormat": {},
      "totalsByVariant": {},
      "attributeReleaseSeries": {
        "os": {},
        "arch": {},
        "format": {},
        "variant": {},
        "version": {}
      },
      "assetAttributesByKey": {}
    }
  },
  {
    "platform": "GitHub",
    "name": "sailpoint-oss/colab-iiqda-plugin-intellij",
    "timestamp": "2025-12-01T00:39:58.223Z",
    "metrics": {
      "stars": 0,
      "forks": 3,
      "watchers": 0,
      "totalIssues": 0,
      "openIssues": 0,
      "closedIssues": 0,
      "language": "Java",
      "size": 464,
      "repositoryAge": 529,
      "lastActivity": 241,
      "releaseCount": 0,
      "totalReleaseDownloads": 0,
      "latestReleaseDownloads": 0,
      "viewsCount": 33,
      "uniqueVisitors": 10,
      "latestRelease": null,
      "clonesCount": 7,
      "topics": 0,
      "license": "MIT License",
      "defaultBranch": "main",
      "downloadsTotal": 0,
      "downloadRange": [],
      "assetTotalsByName": {},
      "assetReleaseSeries": {},
      "assetTotalsByParsedKey": {},
      "totalsByOs": {},
      "totalsByArch": {},
      "totalsByFormat": {},
      "totalsByVariant": {},
      "attributeReleaseSeries": {
        "os": {},
        "arch": {},
        "format": {},
        "variant": {},
        "version": {}
      },
      "assetAttributesByKey": {}
    }
  },
  {
    "platform": "GitHub",
    "name": "sailpoint-oss/colab-saas-conn-identitynow-management",
    "timestamp": "2025-12-01T00:39:58.206Z",
    "metrics": {
      "stars": 6,
      "forks": 8,
      "watchers": 1,
      "totalIssues": 0,
      "openIssues": 0,
      "closedIssues": 0,
      "language": "TypeScript",
      "size": 451,
      "repositoryAge": 796,
      "lastActivity": 268,
      "releaseCount": 0,
      "totalReleaseDownloads": 0,
      "latestReleaseDownloads": 0,
      "viewsCount": 43,
      "uniqueVisitors": 11,
      "latestRelease": null,
      "clonesCount": 4,
      "topics": 0,
      "license": null,
      "defaultBranch": "main",
      "downloadsTotal": 0,
      "downloadRange": [],
      "assetTotalsByName": {},
      "assetReleaseSeries": {},
      "assetTotalsByParsedKey": {},
      "totalsByOs": {},
      "totalsByArch": {},
      "totalsByFormat": {},
      "totalsByVariant": {},
      "attributeReleaseSeries": {
        "os": {},
        "arch": {},
        "format": {},
        "variant": {},
        "version": {}
      },
      "assetAttributesByKey": {}
    }
  },
  {
    "platform": "GitHub",
    "name": "sailpoint-oss/colab-saas-conn-cyber-ark-rbac",
    "timestamp": "2025-12-01T00:39:58.521Z",
    "metrics": {
      "stars": 0,
      "forks": 3,
      "watchers": 0,
      "totalIssues": 0,
      "openIssues": 0,
      "closedIssues": 0,
      "language": "TypeScript",
      "size": 409,
      "repositoryAge": 279,
      "lastActivity": 276,
      "releaseCount": 0,
      "totalReleaseDownloads": 0,
      "latestReleaseDownloads": 0,
      "viewsCount": 18,
      "uniqueVisitors": 9,
      "latestRelease": null,
      "clonesCount": 6,
      "topics": 0,
      "license": "MIT License",
      "defaultBranch": "main",
      "downloadsTotal": 0,
      "downloadRange": [],
      "assetTotalsByName": {},
      "assetReleaseSeries": {},
      "assetTotalsByParsedKey": {},
      "totalsByOs": {},
      "totalsByArch": {},
      "totalsByFormat": {},
      "totalsByVariant": {},
      "attributeReleaseSeries": {
        "os": {},
        "arch": {},
        "format": {},
        "variant": {},
        "version": {}
      },
      "assetAttributesByKey": {}
    }
  },
  {
    "platform": "GitHub",
    "name": "sailpoint-oss/colab-saas-conn-peloton-landview",
    "timestamp": "2025-12-01T00:39:58.227Z",
    "metrics": {
      "stars": 0,
      "forks": 0,
      "watchers": 0,
      "totalIssues": 0,
      "openIssues": 0,
      "closedIssues": 0,
      "language": "TypeScript",
      "size": 607,
      "repositoryAge": 618,
      "lastActivity": 279,
      "releaseCount": 0,
      "totalReleaseDownloads": 0,
      "latestReleaseDownloads": 0,
      "viewsCount": 1,
      "uniqueVisitors": 1,
      "latestRelease": null,
      "clonesCount": 6,
      "topics": 0,
      "license": "MIT License",
      "defaultBranch": "main",
      "downloadsTotal": 0,
      "downloadRange": [],
      "assetTotalsByName": {},
      "assetReleaseSeries": {},
      "assetTotalsByParsedKey": {},
      "totalsByOs": {},
      "totalsByArch": {},
      "totalsByFormat": {},
      "totalsByVariant": {},
      "attributeReleaseSeries": {
        "os": {},
        "arch": {},
        "format": {},
        "variant": {},
        "version": {}
      },
      "assetAttributesByKey": {}
    }
  },
  {
    "platform": "GitHub",
    "name": "sailpoint-oss/colab-workflows",
    "timestamp": "2025-12-01T00:39:58.290Z",
    "metrics": {
      "stars": 13,
      "forks": 16,
      "watchers": 4,
      "totalIssues": 0,
      "openIssues": 0,
      "closedIssues": 0,
      "language": null,
      "size": 481,
      "repositoryAge": 797,
      "lastActivity": 284,
      "releaseCount": 0,
      "totalReleaseDownloads": 0,
      "latestReleaseDownloads": 0,
      "viewsCount": 329,
      "uniqueVisitors": 65,
      "latestRelease": null,
      "clonesCount": 5,
      "topics": 1,
      "license": "MIT License",
      "defaultBranch": "main",
      "downloadsTotal": 0,
      "downloadRange": [],
      "assetTotalsByName": {},
      "assetReleaseSeries": {},
      "assetTotalsByParsedKey": {},
      "totalsByOs": {},
      "totalsByArch": {},
      "totalsByFormat": {},
      "totalsByVariant": {},
      "attributeReleaseSeries": {
        "os": {},
        "arch": {},
        "format": {},
        "variant": {},
        "version": {}
      },
      "assetAttributesByKey": {}
    }
  },
  {
    "platform": "GitHub",
    "name": "sailpoint-oss/colab-show-workgroup-member-plugin",
    "timestamp": "2025-12-01T00:39:58.236Z",
    "metrics": {
      "stars": 0,
      "forks": 2,
      "watchers": 0,
      "totalIssues": 0,
      "openIssues": 0,
      "closedIssues": 0,
      "language": "Java",
      "size": 404,
      "repositoryAge": 307,
      "lastActivity": 292,
      "releaseCount": 0,
      "totalReleaseDownloads": 0,
      "latestReleaseDownloads": 0,
      "viewsCount": 17,
      "uniqueVisitors": 6,
      "latestRelease": null,
      "clonesCount": 4,
      "topics": 0,
      "license": "MIT License",
      "defaultBranch": "main",
      "downloadsTotal": 0,
      "downloadRange": [],
      "assetTotalsByName": {},
      "assetReleaseSeries": {},
      "assetTotalsByParsedKey": {},
      "totalsByOs": {},
      "totalsByArch": {},
      "totalsByFormat": {},
      "totalsByVariant": {},
      "attributeReleaseSeries": {
        "os": {},
        "arch": {},
        "format": {},
        "variant": {},
        "version": {}
      },
      "assetAttributesByKey": {}
    }
  },
  {
    "platform": "GitHub",
    "name": "sailpoint-oss/colab-iiq-custom-loading-spinner",
    "timestamp": "2025-12-01T00:39:58.251Z",
    "metrics": {
      "stars": 0,
      "forks": 1,
      "watchers": 0,
      "totalIssues": 0,
      "openIssues": 0,
      "closedIssues": 0,
      "language": "JavaScript",
      "size": 403,
      "repositoryAge": 327,
      "lastActivity": 321,
      "releaseCount": 1,
      "totalReleaseDownloads": 4,
      "latestReleaseDownloads": 4,
      "viewsCount": 10,
      "uniqueVisitors": 2,
      "latestRelease": "v1.0",
      "clonesCount": 5,
      "topics": 0,
      "license": "MIT License",
      "defaultBranch": "main",
      "downloadsTotal": 4,
      "downloadRange": [
        {
          "day": "2025-01-13T06:49:24Z",
          "downloads": 4,
          "tagName": "v1.0"
        }
      ],
      "assetTotalsByName": {
        "custom_zip": 4
      },
      "assetReleaseSeries": {
        "custom_zip": [
          {
            "tagName": "v1.0",
            "day": "2025-01-13T06:49:24Z",
            "downloads": 4
          }
        ]
      },
      "assetTotalsByParsedKey": {
        "custom_zip": 4
      },
      "totalsByOs": {},
      "totalsByArch": {},
      "totalsByFormat": {
        "zip": 4
      },
      "totalsByVariant": {},
      "attributeReleaseSeries": {
        "os": {},
        "arch": {},
        "format": {
          "zip": {
            "v1.0": 4
          }
        },
        "variant": {},
        "version": {}
      },
      "assetAttributesByKey": {
        "custom_zip": {
          "project": "Custom",
          "format": "zip"
        }
      }
    }
  },
  {
    "platform": "GitHub",
    "name": "sailpoint-oss/colab-isc-auto-loader",
    "timestamp": "2025-12-01T00:39:58.225Z",
    "metrics": {
      "stars": 0,
      "forks": 2,
      "watchers": 0,
      "totalIssues": 0,
      "openIssues": 0,
      "closedIssues": 0,
      "language": null,
      "size": 397,
      "repositoryAge": 355,
      "lastActivity": 355,
      "releaseCount": 0,
      "totalReleaseDownloads": 0,
      "latestReleaseDownloads": 0,
      "viewsCount": 1,
      "uniqueVisitors": 1,
      "latestRelease": null,
      "clonesCount": 4,
      "topics": 0,
      "license": "MIT License",
      "defaultBranch": "main",
      "downloadsTotal": 0,
      "downloadRange": [],
      "assetTotalsByName": {},
      "assetReleaseSeries": {},
      "assetTotalsByParsedKey": {},
      "totalsByOs": {},
      "totalsByArch": {},
      "totalsByFormat": {},
      "totalsByVariant": {},
      "attributeReleaseSeries": {
        "os": {},
        "arch": {},
        "format": {},
        "variant": {},
        "version": {}
      },
      "assetAttributesByKey": {}
    }
  },
  {
    "platform": "GitHub",
    "name": "sailpoint-oss/colab-saas-conn-beyondtrust-privilege-management-cloud",
    "timestamp": "2025-12-01T00:39:58.192Z",
    "metrics": {
      "stars": 0,
      "forks": 1,
      "watchers": 0,
      "totalIssues": 0,
      "openIssues": 0,
      "closedIssues": 0,
      "language": "TypeScript",
      "size": 6415,
      "repositoryAge": 670,
      "lastActivity": 360,
      "releaseCount": 0,
      "totalReleaseDownloads": 0,
      "latestReleaseDownloads": 0,
      "viewsCount": 4,
      "uniqueVisitors": 4,
      "latestRelease": null,
      "clonesCount": 6,
      "topics": 0,
      "license": "MIT License",
      "defaultBranch": "main",
      "downloadsTotal": 0,
      "downloadRange": [],
      "assetTotalsByName": {},
      "assetReleaseSeries": {},
      "assetTotalsByParsedKey": {},
      "totalsByOs": {},
      "totalsByArch": {},
      "totalsByFormat": {},
      "totalsByVariant": {},
      "attributeReleaseSeries": {
        "os": {},
        "arch": {},
        "format": {},
        "variant": {},
        "version": {}
      },
      "assetAttributesByKey": {}
    }
  },
  {
    "platform": "GitHub",
    "name": "sailpoint-oss/colab-provisioning-simulator-plugin",
    "timestamp": "2025-12-01T00:39:58.354Z",
    "metrics": {
      "stars": 2,
      "forks": 1,
      "watchers": 0,
      "totalIssues": 11,
      "openIssues": 8,
      "closedIssues": 3,
      "language": "Java",
      "size": 15199,
      "repositoryAge": 571,
      "lastActivity": 362,
      "releaseCount": 3,
      "totalReleaseDownloads": 11,
      "latestReleaseDownloads": 9,
      "viewsCount": 3,
      "uniqueVisitors": 3,
      "latestRelease": "1.2",
      "clonesCount": 3,
      "topics": 0,
      "license": "MIT License",
      "defaultBranch": "main",
      "downloadsTotal": 11,
      "downloadRange": [
        {
          "day": "2024-05-15T20:42:40Z",
          "downloads": 1,
          "tagName": "1.0"
        },
        {
          "day": "2024-05-30T12:09:13Z",
          "downloads": 1,
          "tagName": "1.1"
        },
        {
          "day": "2024-05-31T10:47:11Z",
          "downloads": 9,
          "tagName": "1.2"
        }
      ],
      "assetTotalsByName": {
        "colab": 6,
        "colab_zip": 4,
        "provisioningsimulator": 1
      },
      "assetReleaseSeries": {
        "colab": [
          {
            "tagName": "1.2",
            "day": "2024-05-31T10:47:11Z",
            "downloads": 5
          },
          {
            "tagName": "1.1",
            "day": "2024-05-30T12:09:13Z",
            "downloads": 1
          }
        ],
        "colab_zip": [
          {
            "tagName": "1.2",
            "day": "2024-05-31T10:47:11Z",
            "downloads": 4
          },
          {
            "tagName": "1.1",
            "day": "2024-05-30T12:09:13Z",
            "downloads": 0
          }
        ],
        "provisioningsimulator": [
          {
            "tagName": "1.0",
            "day": "2024-05-15T20:42:40Z",
            "downloads": 1
          }
        ]
      },
      "assetTotalsByParsedKey": {
        "colab": 6,
        "colab_zip": 4,
        "provisioningsimulator": 1
      },
      "totalsByOs": {},
      "totalsByArch": {},
      "totalsByFormat": {
        "zip": 4
      },
      "totalsByVariant": {},
      "attributeReleaseSeries": {
        "os": {},
        "arch": {},
        "format": {
          "zip": {
            "1.2": 4,
            "1.1": 0
          }
        },
        "variant": {},
        "version": {}
      },
      "assetAttributesByKey": {
        "colab": {
          "project": "colab"
        },
        "colab_zip": {
          "project": "colab",
          "format": "zip"
        },
        "provisioningsimulator": {
          "project": "ProvisioningSimulator"
        }
      }
    }
  },
  {
    "platform": "GitHub",
    "name": "sailpoint-oss/colab-saas-conn-thomsonreuters-document-intelligence",
    "timestamp": "2025-12-01T00:39:58.233Z",
    "metrics": {
      "stars": 1,
      "forks": 1,
      "watchers": 0,
      "totalIssues": 0,
      "openIssues": 0,
      "closedIssues": 0,
      "language": "TypeScript",
      "size": 460,
      "repositoryAge": 370,
      "lastActivity": 363,
      "releaseCount": 0,
      "totalReleaseDownloads": 0,
      "latestReleaseDownloads": 0,
      "viewsCount": 1,
      "uniqueVisitors": 1,
      "latestRelease": null,
      "clonesCount": 4,
      "topics": 0,
      "license": "MIT License",
      "defaultBranch": "main",
      "downloadsTotal": 0,
      "downloadRange": [],
      "assetTotalsByName": {},
      "assetReleaseSeries": {},
      "assetTotalsByParsedKey": {},
      "totalsByOs": {},
      "totalsByArch": {},
      "totalsByFormat": {},
      "totalsByVariant": {},
      "attributeReleaseSeries": {
        "os": {},
        "arch": {},
        "format": {},
        "variant": {},
        "version": {}
      },
      "assetAttributesByKey": {}
    }
  },
  {
    "platform": "GitHub",
    "name": "sailpoint-oss/colab-isc-powershell-task-manager",
    "timestamp": "2025-12-01T00:39:58.590Z",
    "metrics": {
      "stars": 1,
      "forks": 1,
      "watchers": 0,
      "totalIssues": 0,
      "openIssues": 0,
      "closedIssues": 0,
      "language": "PowerShell",
      "size": 526,
      "repositoryAge": 416,
      "lastActivity": 394,
      "releaseCount": 0,
      "totalReleaseDownloads": 0,
      "latestReleaseDownloads": 0,
      "viewsCount": 0,
      "uniqueVisitors": 0,
      "latestRelease": null,
      "clonesCount": 7,
      "topics": 0,
      "license": "MIT License",
      "defaultBranch": "main",
      "downloadsTotal": 0,
      "downloadRange": [],
      "assetTotalsByName": {},
      "assetReleaseSeries": {},
      "assetTotalsByParsedKey": {},
      "totalsByOs": {},
      "totalsByArch": {},
      "totalsByFormat": {},
      "totalsByVariant": {},
      "attributeReleaseSeries": {
        "os": {},
        "arch": {},
        "format": {},
        "variant": {},
        "version": {}
      },
      "assetAttributesByKey": {}
    }
  },
  {
    "platform": "GitHub",
    "name": "sailpoint-oss/colab-saas-conn-delimited-file",
    "timestamp": "2025-12-01T00:39:58.293Z",
    "metrics": {
      "stars": 1,
      "forks": 2,
      "watchers": 0,
      "totalIssues": 0,
      "openIssues": 0,
      "closedIssues": 0,
      "language": "TypeScript",
      "size": 606,
      "repositoryAge": 492,
      "lastActivity": 407,
      "releaseCount": 0,
      "totalReleaseDownloads": 0,
      "latestReleaseDownloads": 0,
      "viewsCount": 0,
      "uniqueVisitors": 0,
      "latestRelease": null,
      "clonesCount": 5,
      "topics": 0,
      "license": "MIT License",
      "defaultBranch": "main",
      "downloadsTotal": 0,
      "downloadRange": [],
      "assetTotalsByName": {},
      "assetReleaseSeries": {},
      "assetTotalsByParsedKey": {},
      "totalsByOs": {},
      "totalsByArch": {},
      "totalsByFormat": {},
      "totalsByVariant": {},
      "attributeReleaseSeries": {
        "os": {},
        "arch": {},
        "format": {},
        "variant": {},
        "version": {}
      },
      "assetAttributesByKey": {}
    }
  },
  {
    "platform": "GitHub",
    "name": "sailpoint-oss/colab-file-upload-utility-automation-scripts",
    "timestamp": "2025-12-01T00:39:58.281Z",
    "metrics": {
      "stars": 1,
      "forks": 2,
      "watchers": 1,
      "totalIssues": 0,
      "openIssues": 0,
      "closedIssues": 0,
      "language": "PowerShell",
      "size": 405,
      "repositoryAge": 437,
      "lastActivity": 425,
      "releaseCount": 0,
      "totalReleaseDownloads": 0,
      "latestReleaseDownloads": 0,
      "viewsCount": 47,
      "uniqueVisitors": 8,
      "latestRelease": null,
      "clonesCount": 3,
      "topics": 0,
      "license": "MIT License",
      "defaultBranch": "main",
      "downloadsTotal": 0,
      "downloadRange": [],
      "assetTotalsByName": {},
      "assetReleaseSeries": {},
      "assetTotalsByParsedKey": {},
      "totalsByOs": {},
      "totalsByArch": {},
      "totalsByFormat": {},
      "totalsByVariant": {},
      "attributeReleaseSeries": {
        "os": {},
        "arch": {},
        "format": {},
        "variant": {},
        "version": {}
      },
      "assetAttributesByKey": {}
    }
  },
  {
    "platform": "GitHub",
    "name": "sailpoint-oss/colab-sailpoint-configuration-manager",
    "timestamp": "2025-12-01T00:39:58.215Z",
    "metrics": {
      "stars": 2,
      "forks": 3,
      "watchers": 1,
      "totalIssues": 0,
      "openIssues": 0,
      "closedIssues": 0,
      "language": "PowerShell",
      "size": 485,
      "repositoryAge": 641,
      "lastActivity": 428,
      "releaseCount": 0,
      "totalReleaseDownloads": 0,
      "latestReleaseDownloads": 0,
      "viewsCount": 3,
      "uniqueVisitors": 3,
      "latestRelease": null,
      "clonesCount": 3,
      "topics": 0,
      "license": "MIT License",
      "defaultBranch": "main",
      "downloadsTotal": 0,
      "downloadRange": [],
      "assetTotalsByName": {},
      "assetReleaseSeries": {},
      "assetTotalsByParsedKey": {},
      "totalsByOs": {},
      "totalsByArch": {},
      "totalsByFormat": {},
      "totalsByVariant": {},
      "attributeReleaseSeries": {
        "os": {},
        "arch": {},
        "format": {},
        "variant": {},
        "version": {}
      },
      "assetAttributesByKey": {}
    }
  },
  {
    "platform": "GitHub",
    "name": "sailpoint-oss/colab-org-chart-plugin",
    "timestamp": "2025-12-01T00:39:58.351Z",
    "metrics": {
      "stars": 0,
      "forks": 1,
      "watchers": 0,
      "totalIssues": 0,
      "openIssues": 0,
      "closedIssues": 0,
      "language": "TypeScript",
      "size": 34236,
      "repositoryAge": 529,
      "lastActivity": 430,
      "releaseCount": 1,
      "totalReleaseDownloads": 38,
      "latestReleaseDownloads": 38,
      "viewsCount": 92,
      "uniqueVisitors": 4,
      "latestRelease": "1.2.0",
      "clonesCount": 6,
      "topics": 0,
      "license": "MIT License",
      "defaultBranch": "main",
      "downloadsTotal": 38,
      "downloadRange": [
        {
          "day": "2024-07-11T15:40:36Z",
          "downloads": 38,
          "tagName": "1.2.0"
        }
      ],
      "assetTotalsByName": {
        "orgchartplugin_zip": 38
      },
      "assetReleaseSeries": {
        "orgchartplugin_zip": [
          {
            "tagName": "1.2.0",
            "day": "2024-07-11T15:40:36Z",
            "downloads": 38
          }
        ]
      },
      "assetTotalsByParsedKey": {
        "orgchartplugin_zip": 38
      },
      "totalsByOs": {},
      "totalsByArch": {},
      "totalsByFormat": {
        "zip": 38
      },
      "totalsByVariant": {},
      "attributeReleaseSeries": {
        "os": {},
        "arch": {},
        "format": {
          "zip": {
            "1.2.0": 38
          }
        },
        "variant": {},
        "version": {}
      },
      "assetAttributesByKey": {
        "orgchartplugin_zip": {
          "project": "orgchartplugin",
          "format": "zip"
        }
      }
    }
  },
  {
    "platform": "GitHub",
    "name": "sailpoint-oss/colab-transforms",
    "timestamp": "2025-12-01T00:39:58.242Z",
    "metrics": {
      "stars": 2,
      "forks": 9,
      "watchers": 0,
      "totalIssues": 0,
      "openIssues": 0,
      "closedIssues": 0,
      "language": null,
      "size": 421,
      "repositoryAge": 797,
      "lastActivity": 431,
      "releaseCount": 0,
      "totalReleaseDownloads": 0,
      "latestReleaseDownloads": 0,
      "viewsCount": 79,
      "uniqueVisitors": 22,
      "latestRelease": null,
      "clonesCount": 6,
      "topics": 1,
      "license": "MIT License",
      "defaultBranch": "main",
      "downloadsTotal": 0,
      "downloadRange": [],
      "assetTotalsByName": {},
      "assetReleaseSeries": {},
      "assetTotalsByParsedKey": {},
      "totalsByOs": {},
      "totalsByArch": {},
      "totalsByFormat": {},
      "totalsByVariant": {},
      "attributeReleaseSeries": {
        "os": {},
        "arch": {},
        "format": {},
        "variant": {},
        "version": {}
      },
      "assetAttributesByKey": {}
    }
  },
  {
    "platform": "GitHub",
    "name": "sailpoint-oss/colab-file-upload-utility",
    "timestamp": "2025-12-01T00:39:58.329Z",
    "metrics": {
      "stars": 5,
      "forks": 8,
      "watchers": 1,
      "totalIssues": 5,
      "openIssues": 3,
      "closedIssues": 2,
      "language": "Java",
      "size": 457,
      "repositoryAge": 796,
      "lastActivity": 445,
      "releaseCount": 2,
      "totalReleaseDownloads": 1724,
      "latestReleaseDownloads": 954,
      "viewsCount": 155,
      "uniqueVisitors": 66,
      "latestRelease": "file-upload-utility-4.1.0",
      "clonesCount": 10,
      "topics": 1,
      "license": "MIT License",
      "defaultBranch": "main",
      "downloadsTotal": 1724,
      "downloadRange": [
        {
          "day": "2024-05-01T16:36:27Z",
          "downloads": 770,
          "tagName": "file-upload-utility-4.0.0"
        },
        {
          "day": "2024-09-11T02:56:25Z",
          "downloads": 954,
          "tagName": "file-upload-utility-4.1.0"
        }
      ],
      "assetTotalsByName": {
        "sailpoint": 1724
      },
      "assetReleaseSeries": {
        "sailpoint": [
          {
            "tagName": "file-upload-utility-4.1.0",
            "day": "2024-09-11T02:56:25Z",
            "downloads": 954
          },
          {
            "tagName": "file-upload-utility-4.0.0",
            "day": "2024-05-01T16:36:27Z",
            "downloads": 770
          }
        ]
      },
      "assetTotalsByParsedKey": {
        "sailpoint": 1724
      },
      "totalsByOs": {},
      "totalsByArch": {},
      "totalsByFormat": {},
      "totalsByVariant": {},
      "attributeReleaseSeries": {
        "os": {},
        "arch": {},
        "format": {},
        "variant": {},
        "version": {}
      },
      "assetAttributesByKey": {
        "sailpoint": {
          "project": "sailpoint"
        }
      }
    }
  },
  {
    "platform": "GitHub",
    "name": "sailpoint-oss/colab-isc-credential-cycling",
    "timestamp": "2025-12-01T00:39:58.280Z",
    "metrics": {
      "stars": 0,
      "forks": 1,
      "watchers": 0,
      "totalIssues": 0,
      "openIssues": 0,
      "closedIssues": 0,
      "language": "C#",
      "size": 4101,
      "repositoryAge": 485,
      "lastActivity": 459,
      "releaseCount": 0,
      "totalReleaseDownloads": 0,
      "latestReleaseDownloads": 0,
      "viewsCount": 5,
      "uniqueVisitors": 1,
      "latestRelease": null,
      "clonesCount": 5,
      "topics": 0,
      "license": "MIT License",
      "defaultBranch": "main",
      "downloadsTotal": 0,
      "downloadRange": [],
      "assetTotalsByName": {},
      "assetReleaseSeries": {},
      "assetTotalsByParsedKey": {},
      "totalsByOs": {},
      "totalsByArch": {},
      "totalsByFormat": {},
      "totalsByVariant": {},
      "attributeReleaseSeries": {
        "os": {},
        "arch": {},
        "format": {},
        "variant": {},
        "version": {}
      },
      "assetAttributesByKey": {}
    }
  },
  {
    "platform": "GitHub",
    "name": "sailpoint-oss/colab-log-level-modifier-plugin",
    "timestamp": "2025-12-01T00:39:58.152Z",
    "metrics": {
      "stars": 1,
      "forks": 2,
      "watchers": 0,
      "totalIssues": 0,
      "openIssues": 0,
      "closedIssues": 0,
      "language": "HTML",
      "size": 584,
      "repositoryAge": 472,
      "lastActivity": 468,
      "releaseCount": 0,
      "totalReleaseDownloads": 0,
      "latestReleaseDownloads": 0,
      "viewsCount": 33,
      "uniqueVisitors": 4,
      "latestRelease": null,
      "clonesCount": 7,
      "topics": 0,
      "license": "MIT License",
      "defaultBranch": "main",
      "downloadsTotal": 0,
      "downloadRange": [],
      "assetTotalsByName": {},
      "assetReleaseSeries": {},
      "assetTotalsByParsedKey": {},
      "totalsByOs": {},
      "totalsByArch": {},
      "totalsByFormat": {},
      "totalsByVariant": {},
      "attributeReleaseSeries": {
        "os": {},
        "arch": {},
        "format": {},
        "variant": {},
        "version": {}
      },
      "assetAttributesByKey": {}
    }
  },
  {
    "platform": "GitHub",
    "name": "sailpoint-oss/colab-valdate-population-plugin",
    "timestamp": "2025-12-01T00:39:58.173Z",
    "metrics": {
      "stars": 0,
      "forks": 0,
      "watchers": 0,
      "totalIssues": 0,
      "openIssues": 0,
      "closedIssues": 0,
      "language": null,
      "size": 397,
      "repositoryAge": 482,
      "lastActivity": 482,
      "releaseCount": 0,
      "totalReleaseDownloads": 0,
      "latestReleaseDownloads": 0,
      "viewsCount": 1,
      "uniqueVisitors": 1,
      "latestRelease": null,
      "clonesCount": 6,
      "topics": 0,
      "license": "MIT License",
      "defaultBranch": "main",
      "downloadsTotal": 0,
      "downloadRange": [],
      "assetTotalsByName": {},
      "assetReleaseSeries": {},
      "assetTotalsByParsedKey": {},
      "totalsByOs": {},
      "totalsByArch": {},
      "totalsByFormat": {},
      "totalsByVariant": {},
      "attributeReleaseSeries": {
        "os": {},
        "arch": {},
        "format": {},
        "variant": {},
        "version": {}
      },
      "assetAttributesByKey": {}
    }
  },
  {
    "platform": "GitHub",
    "name": "sailpoint-oss/colab-identity-photos-plugin",
    "timestamp": "2025-12-01T00:39:58.379Z",
    "metrics": {
      "stars": 0,
      "forks": 0,
      "watchers": 0,
      "totalIssues": 0,
      "openIssues": 0,
      "closedIssues": 0,
      "language": null,
      "size": 397,
      "repositoryAge": 482,
      "lastActivity": 482,
      "releaseCount": 0,
      "totalReleaseDownloads": 0,
      "latestReleaseDownloads": 0,
      "viewsCount": 0,
      "uniqueVisitors": 0,
      "latestRelease": null,
      "clonesCount": 6,
      "topics": 0,
      "license": "MIT License",
      "defaultBranch": "main",
      "downloadsTotal": 0,
      "downloadRange": [],
      "assetTotalsByName": {},
      "assetReleaseSeries": {},
      "assetTotalsByParsedKey": {},
      "totalsByOs": {},
      "totalsByArch": {},
      "totalsByFormat": {},
      "totalsByVariant": {},
      "attributeReleaseSeries": {
        "os": {},
        "arch": {},
        "format": {},
        "variant": {},
        "version": {}
      },
      "assetAttributesByKey": {}
    }
  },
  {
    "platform": "GitHub",
    "name": "sailpoint-oss/colab-community-rest-api-plugin",
    "timestamp": "2025-12-01T00:39:58.277Z",
    "metrics": {
      "stars": 2,
      "forks": 4,
      "watchers": 0,
      "totalIssues": 0,
      "openIssues": 0,
      "closedIssues": 0,
      "language": "Java",
      "size": 642,
      "repositoryAge": 529,
      "lastActivity": 523,
      "releaseCount": 0,
      "totalReleaseDownloads": 0,
      "latestReleaseDownloads": 0,
      "viewsCount": 48,
      "uniqueVisitors": 7,
      "latestRelease": null,
      "clonesCount": 5,
      "topics": 0,
      "license": "MIT License",
      "defaultBranch": "main",
      "downloadsTotal": 0,
      "downloadRange": [],
      "assetTotalsByName": {},
      "assetReleaseSeries": {},
      "assetTotalsByParsedKey": {},
      "totalsByOs": {},
      "totalsByArch": {},
      "totalsByFormat": {},
      "totalsByVariant": {},
      "attributeReleaseSeries": {
        "os": {},
        "arch": {},
        "format": {},
        "variant": {},
        "version": {}
      },
      "assetAttributesByKey": {}
    }
  },
  {
    "platform": "GitHub",
    "name": "sailpoint-oss/colab-saas-conn-beyondtrust-pmcloud-computers",
    "timestamp": "2025-12-01T00:39:58.230Z",
    "metrics": {
      "stars": 1,
      "forks": 2,
      "watchers": 0,
      "totalIssues": 0,
      "openIssues": 0,
      "closedIssues": 0,
      "language": "TypeScript",
      "size": 6252,
      "repositoryAge": 670,
      "lastActivity": 528,
      "releaseCount": 2,
      "totalReleaseDownloads": 0,
      "latestReleaseDownloads": 0,
      "viewsCount": 1,
      "uniqueVisitors": 1,
      "latestRelease": "v1.01",
      "clonesCount": 6,
      "topics": 0,
      "license": "MIT License",
      "defaultBranch": "main",
      "downloadsTotal": 0,
      "downloadRange": [
        {
          "day": "2024-02-23T21:48:30Z",
          "downloads": 0,
          "tagName": "v1.0"
        },
        {
          "day": "2024-04-03T18:40:21Z",
          "downloads": 0,
          "tagName": "v1.01"
        }
      ],
      "assetTotalsByName": {},
      "assetReleaseSeries": {},
      "assetTotalsByParsedKey": {},
      "totalsByOs": {},
      "totalsByArch": {},
      "totalsByFormat": {},
      "totalsByVariant": {},
      "attributeReleaseSeries": {
        "os": {},
        "arch": {},
        "format": {},
        "variant": {},
        "version": {}
      },
      "assetAttributesByKey": {}
    }
  },
  {
    "platform": "GitHub",
    "name": "sailpoint-oss/colab-connector-configurations",
    "timestamp": "2025-12-01T00:39:58.210Z",
    "metrics": {
      "stars": 0,
      "forks": 1,
      "watchers": 0,
      "totalIssues": 0,
      "openIssues": 0,
      "closedIssues": 0,
      "language": null,
      "size": 400,
      "repositoryAge": 529,
      "lastActivity": 529,
      "releaseCount": 0,
      "totalReleaseDownloads": 0,
      "latestReleaseDownloads": 0,
      "viewsCount": 2,
      "uniqueVisitors": 1,
      "latestRelease": null,
      "clonesCount": 5,
      "topics": 0,
      "license": "MIT License",
      "defaultBranch": "main",
      "downloadsTotal": 0,
      "downloadRange": [],
      "assetTotalsByName": {},
      "assetReleaseSeries": {},
      "assetTotalsByParsedKey": {},
      "totalsByOs": {},
      "totalsByArch": {},
      "totalsByFormat": {},
      "totalsByVariant": {},
      "attributeReleaseSeries": {
        "os": {},
        "arch": {},
        "format": {},
        "variant": {},
        "version": {}
      },
      "assetAttributesByKey": {}
    }
  },
  {
    "platform": "GitHub",
    "name": "sailpoint-oss/colab-iiq-hbm-extension-template",
    "timestamp": "2025-12-01T00:39:58.393Z",
    "metrics": {
      "stars": 2,
      "forks": 2,
      "watchers": 0,
      "totalIssues": 0,
      "openIssues": 0,
      "closedIssues": 0,
      "language": "Java",
      "size": 1769,
      "repositoryAge": 585,
      "lastActivity": 557,
      "releaseCount": 0,
      "totalReleaseDownloads": 0,
      "latestReleaseDownloads": 0,
      "viewsCount": 27,
      "uniqueVisitors": 4,
      "latestRelease": null,
      "clonesCount": 4,
      "topics": 0,
      "license": "MIT License",
      "defaultBranch": "main",
      "downloadsTotal": 0,
      "downloadRange": [],
      "assetTotalsByName": {},
      "assetReleaseSeries": {},
      "assetTotalsByParsedKey": {},
      "totalsByOs": {},
      "totalsByArch": {},
      "totalsByFormat": {},
      "totalsByVariant": {},
      "attributeReleaseSeries": {
        "os": {},
        "arch": {},
        "format": {},
        "variant": {},
        "version": {}
      },
      "assetAttributesByKey": {}
    }
  },
  {
    "platform": "GitHub",
    "name": "sailpoint-oss/colab-iiqda",
    "timestamp": "2025-12-01T00:39:58.832Z",
    "metrics": {
      "stars": 5,
      "forks": 9,
      "watchers": 2,
      "totalIssues": 5,
      "openIssues": 4,
      "closedIssues": 1,
      "language": "Java",
      "size": 54240,
      "repositoryAge": 797,
      "lastActivity": 562,
      "releaseCount": 0,
      "totalReleaseDownloads": 0,
      "latestReleaseDownloads": 0,
      "viewsCount": 44,
      "uniqueVisitors": 22,
      "latestRelease": null,
      "clonesCount": 9,
      "topics": 1,
      "license": "MIT License",
      "defaultBranch": "main",
      "downloadsTotal": 0,
      "downloadRange": [],
      "assetTotalsByName": {},
      "assetReleaseSeries": {},
      "assetTotalsByParsedKey": {},
      "totalsByOs": {},
      "totalsByArch": {},
      "totalsByFormat": {},
      "totalsByVariant": {},
      "attributeReleaseSeries": {
        "os": {},
        "arch": {},
        "format": {},
        "variant": {},
        "version": {}
      },
      "assetAttributesByKey": {}
    }
  },
  {
    "platform": "GitHub",
    "name": "sailpoint-oss/colab-announcement-plugin",
    "timestamp": "2025-12-01T00:39:58.420Z",
    "metrics": {
      "stars": 2,
      "forks": 0,
      "watchers": 0,
      "totalIssues": 0,
      "openIssues": 0,
      "closedIssues": 0,
      "language": "CSS",
      "size": 439,
      "repositoryAge": 690,
      "lastActivity": 562,
      "releaseCount": 5,
      "totalReleaseDownloads": 222,
      "latestReleaseDownloads": 103,
      "viewsCount": 38,
      "uniqueVisitors": 5,
      "latestRelease": "v3.1",
      "clonesCount": 3,
      "topics": 0,
      "license": "MIT License",
      "defaultBranch": "main",
      "downloadsTotal": 222,
      "downloadRange": [
        {
          "day": "2024-01-11T16:01:07Z",
          "downloads": 9,
          "tagName": "v1.0"
        },
        {
          "day": "2024-01-12T06:50:11Z",
          "downloads": 11,
          "tagName": "v1.0.1"
        },
        {
          "day": "2024-01-25T13:54:07Z",
          "downloads": 79,
          "tagName": "v2.0"
        },
        {
          "day": "2024-05-12T09:34:14Z",
          "downloads": 20,
          "tagName": "v3.0"
        },
        {
          "day": "2024-05-17T18:30:18Z",
          "downloads": 103,
          "tagName": "v3.1"
        }
      ],
      "assetTotalsByName": {
        "announcement_zip": 222
      },
      "assetReleaseSeries": {
        "announcement_zip": [
          {
            "tagName": "v3.1",
            "day": "2024-05-17T18:30:18Z",
            "downloads": 103
          },
          {
            "tagName": "v3.0",
            "day": "2024-05-12T09:34:14Z",
            "downloads": 20
          },
          {
            "tagName": "v2.0",
            "day": "2024-01-25T13:54:07Z",
            "downloads": 79
          },
          {
            "tagName": "v1.0.1",
            "day": "2024-01-12T06:50:11Z",
            "downloads": 11
          },
          {
            "tagName": "v1.0",
            "day": "2024-01-11T16:01:07Z",
            "downloads": 9
          }
        ]
      },
      "assetTotalsByParsedKey": {
        "announcement_zip": 222
      },
      "totalsByOs": {},
      "totalsByArch": {},
      "totalsByFormat": {
        "zip": 222
      },
      "totalsByVariant": {},
      "attributeReleaseSeries": {
        "os": {},
        "arch": {},
        "format": {
          "zip": {
            "v3.1": 103,
            "v3.0": 20,
            "v2.0": 79,
            "v1.0.1": 11,
            "v1.0": 9
          }
        },
        "variant": {},
        "version": {}
      },
      "assetAttributesByKey": {
        "announcement_zip": {
          "project": "Announcement",
          "format": "zip"
        }
      }
    }
  },
  {
    "platform": "GitHub",
    "name": "sailpoint-oss/colab-identity-details-tweaks-plugin",
    "timestamp": "2025-12-01T00:39:58.409Z",
    "metrics": {
      "stars": 3,
      "forks": 2,
      "watchers": 0,
      "totalIssues": 0,
      "openIssues": 0,
      "closedIssues": 0,
      "language": "JavaScript",
      "size": 432,
      "repositoryAge": 654,
      "lastActivity": 607,
      "releaseCount": 2,
      "totalReleaseDownloads": 7,
      "latestReleaseDownloads": 0,
      "viewsCount": 60,
      "uniqueVisitors": 1,
      "latestRelease": "v2.0",
      "clonesCount": 5,
      "topics": 0,
      "license": "MIT License",
      "defaultBranch": "main",
      "downloadsTotal": 7,
      "downloadRange": [
        {
          "day": "2024-02-21T11:25:15Z",
          "downloads": 7,
          "tagName": "v1.0"
        },
        {
          "day": "2024-04-02T08:06:03Z",
          "downloads": 0,
          "tagName": "v2.0"
        }
      ],
      "assetTotalsByName": {
        "identitydetailstweaks_zip": 7
      },
      "assetReleaseSeries": {
        "identitydetailstweaks_zip": [
          {
            "tagName": "v1.0",
            "day": "2024-02-21T11:25:15Z",
            "downloads": 7
          }
        ]
      },
      "assetTotalsByParsedKey": {
        "identitydetailstweaks_zip": 7
      },
      "totalsByOs": {},
      "totalsByArch": {},
      "totalsByFormat": {
        "zip": 7
      },
      "totalsByVariant": {},
      "attributeReleaseSeries": {
        "os": {},
        "arch": {},
        "format": {
          "zip": {
            "v1.0": 7
          }
        },
        "variant": {},
        "version": {}
      },
      "assetAttributesByKey": {
        "identitydetailstweaks_zip": {
          "project": "IdentityDetailsTweaks",
          "format": "zip"
        }
      }
    }
  },
  {
    "platform": "GitHub",
    "name": "sailpoint-oss/colab-repo-template",
    "timestamp": "2025-12-01T00:39:58.377Z",
    "metrics": {
      "stars": 0,
      "forks": 4,
      "watchers": 2,
      "totalIssues": 0,
      "openIssues": 0,
      "closedIssues": 0,
      "language": null,
      "size": 426,
      "repositoryAge": 1223,
      "lastActivity": 636,
      "releaseCount": 0,
      "totalReleaseDownloads": 0,
      "latestReleaseDownloads": 0,
      "viewsCount": 8,
      "uniqueVisitors": 5,
      "latestRelease": null,
      "clonesCount": 9,
      "topics": 0,
      "license": "MIT License",
      "defaultBranch": "main",
      "downloadsTotal": 0,
      "downloadRange": [],
      "assetTotalsByName": {},
      "assetReleaseSeries": {},
      "assetTotalsByParsedKey": {},
      "totalsByOs": {},
      "totalsByArch": {},
      "totalsByFormat": {},
      "totalsByVariant": {},
      "attributeReleaseSeries": {
        "os": {},
        "arch": {},
        "format": {},
        "variant": {},
        "version": {}
      },
      "assetAttributesByKey": {}
    }
  },
  {
    "platform": "GitHub",
    "name": "sailpoint-oss/colab-identitynow-azure-sentinel",
    "timestamp": "2025-12-01T00:39:58.311Z",
    "metrics": {
      "stars": 0,
      "forks": 2,
      "watchers": 0,
      "totalIssues": 0,
      "openIssues": 0,
      "closedIssues": 0,
      "language": "Python",
      "size": 8940,
      "repositoryAge": 789,
      "lastActivity": 648,
      "releaseCount": 0,
      "totalReleaseDownloads": 0,
      "latestReleaseDownloads": 0,
      "viewsCount": 40,
      "uniqueVisitors": 2,
      "latestRelease": null,
      "clonesCount": 6,
      "topics": 1,
      "license": "MIT License",
      "defaultBranch": "main",
      "downloadsTotal": 0,
      "downloadRange": [],
      "assetTotalsByName": {},
      "assetReleaseSeries": {},
      "assetTotalsByParsedKey": {},
      "totalsByOs": {},
      "totalsByArch": {},
      "totalsByFormat": {},
      "totalsByVariant": {},
      "attributeReleaseSeries": {
        "os": {},
        "arch": {},
        "format": {},
        "variant": {},
        "version": {}
      },
      "assetAttributesByKey": {}
    }
  },
  {
    "platform": "GitHub",
    "name": "sailpoint-oss/colab-sailpoint-rule-restriction-vs-code-plugin",
    "timestamp": "2025-12-01T00:39:58.275Z",
    "metrics": {
      "stars": 0,
      "forks": 2,
      "watchers": 0,
      "totalIssues": 0,
      "openIssues": 0,
      "closedIssues": 0,
      "language": "TypeScript",
      "size": 417,
      "repositoryAge": 668,
      "lastActivity": 654,
      "releaseCount": 0,
      "totalReleaseDownloads": 0,
      "latestReleaseDownloads": 0,
      "viewsCount": 5,
      "uniqueVisitors": 1,
      "latestRelease": null,
      "clonesCount": 5,
      "topics": 0,
      "license": "MIT License",
      "defaultBranch": "main",
      "downloadsTotal": 0,
      "downloadRange": [],
      "assetTotalsByName": {},
      "assetReleaseSeries": {},
      "assetTotalsByParsedKey": {},
      "totalsByOs": {},
      "totalsByArch": {},
      "totalsByFormat": {},
      "totalsByVariant": {},
      "attributeReleaseSeries": {
        "os": {},
        "arch": {},
        "format": {},
        "variant": {},
        "version": {}
      },
      "assetAttributesByKey": {}
    }
  },
  {
    "platform": "GitHub",
    "name": "sailpoint-oss/colab-saas-conn-beyondtrust-representatives",
    "timestamp": "2025-12-01T00:39:58.304Z",
    "metrics": {
      "stars": 1,
      "forks": 1,
      "watchers": 0,
      "totalIssues": 0,
      "openIssues": 0,
      "closedIssues": 0,
      "language": "TypeScript",
      "size": 10753,
      "repositoryAge": 670,
      "lastActivity": 668,
      "releaseCount": 0,
      "totalReleaseDownloads": 0,
      "latestReleaseDownloads": 0,
      "viewsCount": 7,
      "uniqueVisitors": 4,
      "latestRelease": null,
      "clonesCount": 5,
      "topics": 0,
      "license": "MIT License",
      "defaultBranch": "main",
      "downloadsTotal": 0,
      "downloadRange": [],
      "assetTotalsByName": {},
      "assetReleaseSeries": {},
      "assetTotalsByParsedKey": {},
      "totalsByOs": {},
      "totalsByArch": {},
      "totalsByFormat": {},
      "totalsByVariant": {},
      "attributeReleaseSeries": {
        "os": {},
        "arch": {},
        "format": {},
        "variant": {},
        "version": {}
      },
      "assetAttributesByKey": {}
    }
  },
  {
    "platform": "GitHub",
    "name": "sailpoint-oss/colab-reports",
    "timestamp": "2025-12-01T00:39:58.223Z",
    "metrics": {
      "stars": 1,
      "forks": 1,
      "watchers": 0,
      "totalIssues": 0,
      "openIssues": 0,
      "closedIssues": 0,
      "language": "Java",
      "size": 411,
      "repositoryAge": 755,
      "lastActivity": 754,
      "releaseCount": 0,
      "totalReleaseDownloads": 0,
      "latestReleaseDownloads": 0,
      "viewsCount": 35,
      "uniqueVisitors": 5,
      "latestRelease": null,
      "clonesCount": 3,
      "topics": 0,
      "license": "MIT License",
      "defaultBranch": "main",
      "downloadsTotal": 0,
      "downloadRange": [],
      "assetTotalsByName": {},
      "assetReleaseSeries": {},
      "assetTotalsByParsedKey": {},
      "totalsByOs": {},
      "totalsByArch": {},
      "totalsByFormat": {},
      "totalsByVariant": {},
      "attributeReleaseSeries": {
        "os": {},
        "arch": {},
        "format": {},
        "variant": {},
        "version": {}
      },
      "assetAttributesByKey": {}
    }
  },
  {
    "platform": "GitHub",
    "name": "sailpoint-oss/colab-rules",
    "timestamp": "2025-12-01T00:39:58.299Z",
    "metrics": {
      "stars": 3,
      "forks": 7,
      "watchers": 0,
      "totalIssues": 0,
      "openIssues": 0,
      "closedIssues": 0,
      "language": null,
      "size": 409,
      "repositoryAge": 797,
      "lastActivity": 755,
      "releaseCount": 0,
      "totalReleaseDownloads": 0,
      "latestReleaseDownloads": 0,
      "viewsCount": 17,
      "uniqueVisitors": 10,
      "latestRelease": null,
      "clonesCount": 3,
      "topics": 1,
      "license": "MIT License",
      "defaultBranch": "main",
      "downloadsTotal": 0,
      "downloadRange": [],
      "assetTotalsByName": {},
      "assetReleaseSeries": {},
      "assetTotalsByParsedKey": {},
      "totalsByOs": {},
      "totalsByArch": {},
      "totalsByFormat": {},
      "totalsByVariant": {},
      "attributeReleaseSeries": {
        "os": {},
        "arch": {},
        "format": {},
        "variant": {},
        "version": {}
      },
      "assetAttributesByKey": {}
    }
  },
  {
    "platform": "GitHub",
    "name": "sailpoint-oss/colab-proofpoint-plugin",
    "timestamp": "2025-12-01T00:39:58.294Z",
    "metrics": {
      "stars": 1,
      "forks": 1,
      "watchers": 0,
      "totalIssues": 0,
      "openIssues": 0,
      "closedIssues": 0,
      "language": "Java",
      "size": 608,
      "repositoryAge": 795,
      "lastActivity": 782,
      "releaseCount": 0,
      "totalReleaseDownloads": 0,
      "latestReleaseDownloads": 0,
      "viewsCount": 0,
      "uniqueVisitors": 0,
      "latestRelease": null,
      "clonesCount": 3,
      "topics": 1,
      "license": "MIT License",
      "defaultBranch": "main",
      "downloadsTotal": 0,
      "downloadRange": [],
      "assetTotalsByName": {},
      "assetReleaseSeries": {},
      "assetTotalsByParsedKey": {},
      "totalsByOs": {},
      "totalsByArch": {},
      "totalsByFormat": {},
      "totalsByVariant": {},
      "attributeReleaseSeries": {
        "os": {},
        "arch": {},
        "format": {},
        "variant": {},
        "version": {}
      },
      "assetAttributesByKey": {}
    }
  },
  {
    "platform": "GitHub",
    "name": "sailpoint-oss/colab-saas-conn-rambase-cloud-erp",
    "timestamp": "2025-12-01T00:39:58.355Z",
    "metrics": {
      "stars": 0,
      "forks": 1,
      "watchers": 0,
      "totalIssues": 0,
      "openIssues": 0,
      "closedIssues": 0,
      "language": "TypeScript",
      "size": 406,
      "repositoryAge": 796,
      "lastActivity": 787,
      "releaseCount": 0,
      "totalReleaseDownloads": 0,
      "latestReleaseDownloads": 0,
      "viewsCount": 1,
      "uniqueVisitors": 1,
      "latestRelease": null,
      "clonesCount": 6,
      "topics": 1,
      "license": "MIT License",
      "defaultBranch": "main",
      "downloadsTotal": 0,
      "downloadRange": [],
      "assetTotalsByName": {},
      "assetReleaseSeries": {},
      "assetTotalsByParsedKey": {},
      "totalsByOs": {},
      "totalsByArch": {},
      "totalsByFormat": {},
      "totalsByVariant": {},
      "attributeReleaseSeries": {
        "os": {},
        "arch": {},
        "format": {},
        "variant": {},
        "version": {}
      },
      "assetAttributesByKey": {}
    }
  },
  {
    "platform": "GitHub",
    "name": "sailpoint-oss/colab-saas-conn-beyondtrust-epm",
    "timestamp": "2025-12-01T00:39:58.319Z",
    "metrics": {
      "stars": 0,
      "forks": 1,
      "watchers": 0,
      "totalIssues": 0,
      "openIssues": 0,
      "closedIssues": 0,
      "language": null,
      "size": 399,
      "repositoryAge": 796,
      "lastActivity": 789,
      "releaseCount": 0,
      "totalReleaseDownloads": 0,
      "latestReleaseDownloads": 0,
      "viewsCount": 1,
      "uniqueVisitors": 1,
      "latestRelease": null,
      "clonesCount": 6,
      "topics": 1,
      "license": "MIT License",
      "defaultBranch": "main",
      "downloadsTotal": 0,
      "downloadRange": [],
      "assetTotalsByName": {},
      "assetReleaseSeries": {},
      "assetTotalsByParsedKey": {},
      "totalsByOs": {},
      "totalsByArch": {},
      "totalsByFormat": {},
      "totalsByVariant": {},
      "attributeReleaseSeries": {
        "os": {},
        "arch": {},
        "format": {},
        "variant": {},
        "version": {}
      },
      "assetAttributesByKey": {}
    }
  },
  {
    "platform": "GitHub",
    "name": "sailpoint-oss/colab-saas-conn-beyondtrust-pra",
    "timestamp": "2025-12-01T00:39:58.256Z",
    "metrics": {
      "stars": 0,
      "forks": 1,
      "watchers": 0,
      "totalIssues": 0,
      "openIssues": 0,
      "closedIssues": 0,
      "language": null,
      "size": 399,
      "repositoryAge": 796,
      "lastActivity": 789,
      "releaseCount": 0,
      "totalReleaseDownloads": 0,
      "latestReleaseDownloads": 0,
      "viewsCount": 1,
      "uniqueVisitors": 1,
      "latestRelease": null,
      "clonesCount": 6,
      "topics": 1,
      "license": "MIT License",
      "defaultBranch": "main",
      "downloadsTotal": 0,
      "downloadRange": [],
      "assetTotalsByName": {},
      "assetReleaseSeries": {},
      "assetTotalsByParsedKey": {},
      "totalsByOs": {},
      "totalsByArch": {},
      "totalsByFormat": {},
      "totalsByVariant": {},
      "attributeReleaseSeries": {
        "os": {},
        "arch": {},
        "format": {},
        "variant": {},
        "version": {}
      },
      "assetAttributesByKey": {}
    }
  },
  {
    "platform": "GitHub",
    "name": "sailpoint-oss/colab-saas-conn-proofpoint",
    "timestamp": "2025-12-01T00:39:58.260Z",
    "metrics": {
      "stars": 0,
      "forks": 2,
      "watchers": 0,
      "totalIssues": 0,
      "openIssues": 0,
      "closedIssues": 0,
      "language": null,
      "size": 399,
      "repositoryAge": 795,
      "lastActivity": 789,
      "releaseCount": 0,
      "totalReleaseDownloads": 0,
      "latestReleaseDownloads": 0,
      "viewsCount": 1,
      "uniqueVisitors": 1,
      "latestRelease": null,
      "clonesCount": 7,
      "topics": 1,
      "license": "MIT License",
      "defaultBranch": "main",
      "downloadsTotal": 0,
      "downloadRange": [],
      "assetTotalsByName": {},
      "assetReleaseSeries": {},
      "assetTotalsByParsedKey": {},
      "totalsByOs": {},
      "totalsByArch": {},
      "totalsByFormat": {},
      "totalsByVariant": {},
      "attributeReleaseSeries": {
        "os": {},
        "arch": {},
        "format": {},
        "variant": {},
        "version": {}
      },
      "assetAttributesByKey": {}
    }
  }
]